qa_analytics_insights/__init__.py
qa_analytics_insights/_version.py
qa_analytics_insights/cli.py
qa_analytics_insights/data_classes.py
qa_analytics_insights/log.py
qa_analytics_insights/parser.py
qa_analytics_insights/patch_fetcher.py
qa_analytics_insights/result_analyzer.py
qa_analytics_insights/result_visualizer.py
qa_analytics_insights/xml_filter.py
qa_analytics_insights/xml_loader.py
qa_analytics_insights/xml_parser.py
qa_analytics_insights/xml_processor.py
qa_analytics_insights/xml_tag_finder.py
qa_analytics_insights-1.0.3.dist-info/METADATA
qa_analytics_insights-1.0.3.dist-info/WHEEL
qa_analytics_insights-1.0.3.dist-info/entry_points.txt
qa_analytics_insights-1.0.3.dist-info/licenses/AUTHORS.rst
qa_analytics_insights-1.0.3.dist-info/licenses/LICENSE.txt
qa_analytics_insights-1.0.3.dist-info/RECORD
