Metadata-Version: 2.1
Name: qa-analytics-insights
Version: 1.0.3
Summary: Analyze and visualize Quality Assurance data
Project-URL: Documentation, https://qa-analytics-insights.readthedocs.io/en/latest/
Project-URL: Issues, https://github.com/aydabd/qa-analytics-insights/issues
Project-URL: Source, https://github.com/aydabd/qa-analytics-insights
Author-email: Aydin Abdi <ayabd18@ingka.com>
License-Expression: MIT
License-File: AUTHORS.rst
License-File: LICENSE.txt
Keywords: analytics,assurance,black,conda,coverage,data,github,hatch,hatch-vcs,hatchling,html,insights,isort,loguru,matplotlib,mypy,nosetests,pip,pre-commit,pylint,pypi,pytest,pytest-cov,pytest-metadata,pytest-xdist,python,qa,quality,sphinx,sphinx-autodoc-typehints,sphinx-rtd-theme,testing,visualize,xml
Classifier: Development Status :: 5 - Production/Stable
Classifier: Operating System :: OS Independent
Classifier: Programming Language :: Python
Classifier: Programming Language :: Python :: 3.9
Classifier: Programming Language :: Python :: 3.10
Classifier: Programming Language :: Python :: 3.11
Classifier: Topic :: Software Development :: Libraries :: Python Modules
Classifier: Topic :: Software Development :: Quality Assurance
Classifier: Topic :: Software Development :: Testing
Classifier: Topic :: Utilities
Classifier: Typing :: Typed
Requires-Python: >=3.9
Requires-Dist: loguru
Requires-Dist: matplotlib
